movefiletoextensionfolder/__init__.py
movefiletoextensionfolder/movefile.py
movefiletoextensionfolder-1.0.2.dist-info/LICENSE
movefiletoextensionfolder-1.0.2.dist-info/METADATA
movefiletoextensionfolder-1.0.2.dist-info/WHEEL
movefiletoextensionfolder-1.0.2.dist-info/top_level.txt
movefiletoextensionfolder-1.0.2.dist-info/RECORD
