Metadata-Version: 2.1
Name: movefiletoextensionfolder
Version: 1.0.2
Summary: It will move all files in the source path to their respective ext folder in destination path provided
Home-page: https://github.com/bhaskarkh/movefiletoextensionfolder
Author: kumar bhaskar
Author-email: bhaskar646@gmail.com
License: MIT
Platform: UNKNOWN
Classifier: License :: OSI Approved :: MIT License
Classifier: Programming Language :: Python :: 3.6
Classifier: Programming Language :: Python :: 3.7
Classifier: Programming Language :: Python :: 3.8
Requires-Dist: pyttsx3 (==2.6)
